COPYING
COPYING.LESSER
MANIFEST.in
README.rst
pyproject.toml
setup.cfg
setup.py
Py6S/__init__.py
Py6S/lut_trial.py
Py6S/outputs.py
Py6S/sixs.py
Py6S/sixs_exceptions.py
Py6S.egg-info/PKG-INFO
Py6S.egg-info/SOURCES.txt
Py6S.egg-info/dependency_links.txt
Py6S.egg-info/requires.txt
Py6S.egg-info/top_level.txt
Py6S/Params/__init__.py
Py6S/Params/aeroprofile.py
Py6S/Params/altitudes.py
Py6S/Params/atmoscorr.py
Py6S/Params/atmosprofile.py
Py6S/Params/geometry.py
Py6S/Params/ground_reflectance.py
Py6S/Params/wavelength.py
Py6S/SixSHelpers/__init__.py
Py6S/SixSHelpers/aeronet.py
Py6S/SixSHelpers/all_angles.py
Py6S/SixSHelpers/all_wavelengths.py
Py6S/SixSHelpers/radiosonde.py
Py6S/SixSHelpers/spectra.py