Metadata-Version: 2.1
Name: Py6S
Version: 1.9.2
Summary: A wrapper for the 6S Radiative Transfer Model to make it easy to run simulations with a variety of input parameters, and to produce outputs in an easily processable form.
Home-page: http://py6s.rtwilson.com/
Author: Robin Wilson
Author-email: robin@rtwilson.com
License: GPL
Platform: UNKNOWN
Classifier: Development Status :: 5 - Production/Stable
Classifier: Intended Audience :: Science/Research
Classifier: Topic :: Scientific/Engineering :: Atmospheric Science
Classifier: Topic :: Scientific/Engineering :: Physics
Classifier: Topic :: Software Development :: Libraries :: Python Modules
Classifier: License :: OSI Approved :: GNU Library or Lesser General Public License (LGPL)
Classifier: Programming Language :: Python
Classifier: Programming Language :: Python :: 3
Requires-Python: >=3
License-File: COPYING
License-File: COPYING.LESSER
